{"aggregateDatalog":false,"autoSize":true,"condition":true,"conditionContinuous":false,"connection":"script","defaultDatalog":false,"enableDataFilter":true,"hideDatalog":false,"id":2,"keys":[],"mapID":{"map":{"currentPosition":{"id":1,"sent":true}}},"maxID":1,"maxSize":12.502971729805155,"name":"DLG_","olderThen":31536000,"refreshLog":1000,"refreshRead":5000,"samplesAfter":0,"samplesBefore":0,"scriptDatalog":true,"tags":[{"alias":"","align":"left","deltaAbs":0.0,"description":"","descriptionLangs":{},"digital":false,"empty":true,"format":"#.##","hysteresis":false,"id":1,"key":false,"name":"currentPosition","nameLangs":{},"subType":0,"tag":"","type":0,"unit":"","unitLangs":{}}],"viewAccess":-1}